{"name":"5334project","tagline":"Data mining Final Project ","body":"Project on Yelp Dataset Challenge:\r\nWe are finding the terms that are most commonly seen in reviews of a restaurant classified on the ratings. These terms are the important terms for starting a new venture in restaurant business of a particular city. The other thing that we are working is on trending food that we mine from the review data. ","google":"","note":"Don't delete this file! It's used internally to help with page regeneration."}